README
setup.py
Worklog.egg-info/PKG-INFO
Worklog.egg-info/SOURCES.txt
Worklog.egg-info/dependency_links.txt
Worklog.egg-info/requires.txt
Worklog.egg-info/top_level.txt
worklog/__init__.py
worklog/admin.py
worklog/admin_filter.py
worklog/app_settings.py
worklog/forms.py
worklog/models.py
worklog/tasks.py
worklog/tests.py
worklog/timesheet.py
worklog/urls.py
worklog/views.py