Metadata-Version: 1.1
Name: Worklog
Version: 0.8
Summary: A Django based, hourly work logging app which supports job coding, view filtering, csv report generation and an e-mail reminder system
Home-page: https://www.fi.ncsu.edu/
Author: Brian Bouterse
Author-email: bmbouter@gmail.com
License: UNKNOWN
Keywords: Work logging,Report,Email reminder
Platform: UNKNOWN
Classifier: Development Status :: 4 - Beta
Classifier: Topic :: Utilities
Classifier: License :: OSI Approved :: BSD License
